grok_api.py
grok_api-0.1.1.dist-info/METADATA
grok_api-0.1.1.dist-info/WHEEL
grok_api-0.1.1.dist-info/top_level.txt
grok_api-0.1.1.dist-info/RECORD
