Metadata-Version: 2.2
Name: grok-api
Version: 0.1.1
Summary: A simple Python wrapper for interacting with the unofficial Grok API.
Home-page: https://github.com/savasoglu/grok-api
Author: K
Author-email: 109984658+savasoglu@users.noreply.github.com
Classifier: Programming Language :: Python :: 3
Classifier: License :: OSI Approved :: MIT License
Classifier: Operating System :: OS Independent
Requires-Python: >=3.6
Requires-Dist: requests
Requires-Dist: curl_cffi
Dynamic: author
Dynamic: author-email
Dynamic: classifier
Dynamic: description
Dynamic: description-content-type
Dynamic: home-page
Dynamic: requires-dist
Dynamic: requires-python
Dynamic: summary
